webp_support/__init__.py
webp_support/webp_support.c
webp_support/webp_support.cpython-39-darwin.so
webp_support/webp_support.pxd
webp_support/webp_support.pyi
webp_support/webp_support.pyx
webp_support/webp_support_c.c
webp_support/webp_support_c.h
webp_support-0.3.0.dist-info/LICENSE
webp_support-0.3.0.dist-info/METADATA
webp_support-0.3.0.dist-info/WHEEL
webp_support-0.3.0.dist-info/top_level.txt
webp_support-0.3.0.dist-info/RECORD
